struct2model/__init__.py
struct2model/main.py
struct2model-0.1.0.dist-info/METADATA
struct2model-0.1.0.dist-info/WHEEL
struct2model-0.1.0.dist-info/RECORD
